{
  "type": "FeatureCollection",
  "features": [
    {
      "type": "Feature",
      "geometry": {
        "type": "LineString",
        "coordinates": [
          [
            114.15967387736471,
            26.5652665493578
          ],
          [
            114.15967507339279,
            26.565268661690265
          ],
          [
            114.15967626942087,
            26.565270774022718
          ],
          [
            114.1596791960218,
            26.565273941563774
          ],
          [
            114.15968212262275,
            26.565277109104834
          ],
          [
            114.15968657966923,
            26.565279062108768
          ],
          [
            114.1596891004108,
            26.56527973650575
          ],
          [
            114.15968903148577,
            26.565280051685967
          ],
          [
            114.15968764220742,
            26.565280437328077
          ],
          [
            114.15968625292902,
            26.56528082297018
          ],
          [
            114.15968520846293,
            26.565280967271576
          ],
          [
            114.15968308491243,
            26.565281066954668
          ],
          [
            114.1596769872897,
            26.56528125791422
          ],
          [
            114.15967632544701,
            26.56527907392871
          ],
          [
            114.15967610727932,
            26.565278354006523
          ],
          [
            114.15967603536322,
            26.565278116693612
          ],
          [
            114.15967601165704,
            26.56527803846653
          ],
          [
            114.1596760038426,
            26.565278012679997
          ],
          [
            114.15967600126665,
            26.565278004179802
          ],
          [
            114.15967600041756,
            26.565278001377827
          ],
          [
            114.15967600013764,
            26.565278000454192
          ],
          [
            114.15967600004535,
            26.56527800014973
          ],
          [
            114.15967600001495,
            26.565278000049357
          ],
          [
            114.15967600000494,
            26.565278000016278
          ],
          [
            114.15967600000162,
            26.565278000005378
          ],
          [
            114.15967600000056,
            26.565278000001804
          ],
          [
            114.1596760000002,
            26.565278000000657
          ],
          [
            114.15967600000013,
            26.5652780000004
          ],
          [
            114.15967600000003,
            26.565278000000138
          ],
          [
            114.15967600000002,
            26.565278000000053
          ],
          [
            114.159676,
            26.565278000000024
          ],
          [
            114.159676,
            26.565278000000013
          ],
          [
            114.159676,
            26.56527800000001
          ],
          [
            114.159676,
            26.56527800000001
          ],
          [
            114.159676,
            26.56527800000001
          ],
          [
            114.159676,
            26.56527800000001
          ],
          [
            114.159676,
            26.56527800000001
          ],
          [
            114.159676,
            26.56527800000001
          ],
          [
            114.159676,
            26.56527800000001
          ],
          [
            114.159676,
            26.56527800000001
          ],
          [
            114.159676,
            26.56527800000001
          ],
          [
            114.159676,
            26.56527800000001
          ],
          [
            114.159676,
            26.56527800000001
          ],
          [
            114.159676,
            26.56527800000001
          ],
          [
            114.159676,
            26.56527800000001
          ],
          [
            114.159676,
            26.56527800000001
          ],
          [
            114.159676,
            26.56527800000001
          ],
          [
            114.159676,
            26.56527800000001
          ],
          [
            114.159676,
            26.56527800000001
          ],
          [
            114.159676,
            26.56527800000001
          ],
          [
            114.159676,
            26.56527800000001
          ],
          [
            114.159676,
            26.56527800000001
          ],
          [
            114.159676,
            26.56527800000001
          ],
          [
            114.159676,
            26.56527800000001
          ],
          [
            114.159676,
            26.56527800000001
          ],
          [
            114.159676,
            26.56527800000001
          ],
          [
            114.159676,
            26.56527800000001
          ],
          [
            114.159676,
            26.56527800000001
          ],
          [
            114.159676,
            26.56527800000001
          ],
          [
            114.159676,
            26.56527800000001
          ],
          [
            114.159676,
            26.56527800000001
          ],
          [
            114.159676,
            26.56527800000001
          ],
          [
            114.159676,
            26.56527800000001
          ],
          [
            114.159676,
            26.56527800000001
          ],
          [
            114.159676,
            26.56527800000001
          ],
          [
            114.159676,
            26.56527800000001
          ],
          [
            114.159676,
            26.56527800000001
          ],
          [
            114.159676,
            26.56527800000001
          ],
          [
            114.159676,
            26.56527800000001
          ],
          [
            114.159676,
            26.56527800000001
          ],
          [
            114.159676,
            26.56527800000001
          ],
          [
            114.159676,
            26.56527800000001
          ],
          [
            114.159676,
            26.56527800000001
          ],
          [
            114.159676,
            26.56527800000001
          ],
          [
            114.159676,
            26.56527800000001
          ],
          [
            114.159676,
            26.56527800000001
          ],
          [
            114.159676,
            26.56527800000001
          ],
          [
            114.159676,
            26.56527800000001
          ],
          [
            114.159676,
            26.56527800000001
          ],
          [
            114.159676,
            26.56527800000001
          ],
          [
            114.159676,
            26.56527800000001
          ],
          [
            114.159676,
            26.56527800000001
          ],
          [
            114.159676,
            26.56527800000001
          ],
          [
            114.159676,
            26.56527800000001
          ],
          [
            114.159676,
            26.56527800000001
          ],
          [
            114.159676,
            26.56527800000001
          ],
          [
            114.159676,
            26.56527800000001
          ],
          [
            114.159676,
            26.56527800000001
          ],
          [
            114.159676,
            26.56527800000001
          ],
          [
            114.159676,
            26.56527800000001
          ],
          [
            114.159676,
            26.56527800000001
          ],
          [
            114.159676,
            26.56527800000001
          ],
          [
            114.159676,
            26.56527800000001
          ],
          [
            114.159676,
            26.56527800000001
          ],
          [
            114.159676,
            26.56527800000001
          ],
          [
            114.159676,
            26.56527800000001
          ],
          [
            114.159676,
            26.56527800000001
          ],
          [
            114.159676,
            26.56527800000001
          ],
          [
            114.159676,
            26.56527800000001
          ],
          [
            114.159676,
            26.56527800000001
          ],
          [
            114.159676,
            26.56527800000001
          ],
          [
            114.159676,
            26.56527800000001
          ],
          [
            114.159676,
            26.56527800000001
          ],
          [
            114.159676,
            26.56527800000001
          ],
          [
            114.159676,
            26.56527800000001
          ],
          [
            114.159676,
            26.56527800000001
          ],
          [
            114.159676,
            26.56527800000001
          ],
          [
            114.159676,
            26.56527800000001
          ],
          [
            114.159676,
            26.56527800000001
          ],
          [
            114.159676,
            26.56527800000001
          ],
          [
            114.159676,
            26.56527800000001
          ],
          [
            114.159676,
            26.56527800000001
          ],
          [
            114.159676,
            26.56527800000001
          ],
          [
            114.159676,
            26.56527800000001
          ],
          [
            114.159676,
            26.56527800000001
          ],
          [
            114.159676,
            26.56527800000001
          ],
          [
            114.159676,
            26.56527800000001
          ],
          [
            114.159676,
            26.56527800000001
          ],
          [
            114.159676,
            26.56527800000001
          ],
          [
            114.159676,
            26.56527800000001
          ],
          [
            114.159676,
            26.56527800000001
          ],
          [
            114.159676,
            26.56527800000001
          ],
          [
            114.159676,
            26.56527800000001
          ],
          [
            114.159676,
            26.56527800000001
          ],
          [
            114.159676,
            26.56527800000001
          ],
          [
            114.159676,
            26.56527800000001
          ],
          [
            114.159676,
            26.56527800000001
          ],
          [
            114.159676,
            26.56527800000001
          ],
          [
            114.159676,
            26.56527800000001
          ],
          [
            114.159676,
            26.56527800000001
          ],
          [
            114.159676,
            26.56527800000001
          ],
          [
            114.159676,
            26.56527800000001
          ],
          [
            114.159676,
            26.56527800000001
          ],
          [
            114.159676,
            26.56527800000001
          ],
          [
            114.159676,
            26.56527800000001
          ],
          [
            114.159676,
            26.56527800000001
          ],
          [
            114.159676,
            26.56527800000001
          ],
          [
            114.159676,
            26.56527800000001
          ],
          [
            114.159676,
            26.56527800000001
          ],
          [
            114.159676,
            26.56527800000001
          ],
          [
            114.159676,
            26.56527800000001
          ],
          [
            114.159676,
            26.56527800000001
          ],
          [
            114.159676,
            26.56527800000001
          ],
          [
            114.159676,
            26.56527800000001
          ],
          [
            114.159676,
            26.56527800000001
          ],
          [
            114.159676,
            26.56527800000001
          ],
          [
            114.159676,
            26.56527800000001
          ],
          [
            114.159676,
            26.56527800000001
          ],
          [
            114.159676,
            26.56527800000001
          ],
          [
            114.159676,
            26.56527800000001
          ],
          [
            114.159676,
            26.56527800000001
          ],
          [
            114.159676,
            26.56527800000001
          ],
          [
            114.159676,
            26.56527800000001
          ],
          [
            114.159676,
            26.56527800000001
          ],
          [
            114.159676,
            26.56527800000001
          ],
          [
            114.159676,
            26.56527800000001
          ],
          [
            114.159676,
            26.56527800000001
          ],
          [
            114.159676,
            26.565278000000006
          ],
          [
            114.159676,
            26.565277999999992
          ],
          [
            114.15967600000002,
            26.565277999999953
          ],
          [
            114.15967600000006,
            26.56527799999984
          ],
          [
            114.15967600000015,
            26.56527799999949
          ],
          [
            114.15967600000046,
            26.565277999998433
          ],
          [
            114.15967600000141,
            26.565277999995214
          ],
          [
            114.15967600000424,
            26.565277999985447
          ],
          [
            114.15967600001284,
            26.56527799995585
          ],
          [
            114.15967600003898,
            26.565277999866037
          ],
          [
            114.15967600011824,
            26.56527799959359
          ],
          [
            114.1596760003587,
            26.56527799876709
          ],
          [
            114.15967600108809,
            26.56527799625976
          ],
          [
            114.15967600330086,
            26.565277988653435
          ],
          [
            114.15967601001358,
            26.56527796557857
          ],
          [
            114.1596760303776,
            26.565277895577736
          ],
          [
            114.15967609215464,
            26.56527768322035
          ],
          [
            114.15967627956378,
            26.565277039004325
          ],
          [
            114.15967684809543,
            26.56527508468433
          ],
          [
            114.15967857281484,
            26.56526915597951
          ],
          [
            114.15968380498978,
            26.565251170418865
          ],
          [
            114.1596996775164,
            26.56519660868889
          ],
          [
            114.15970693075336,
            26.565164689213205
          ],
          [
            114.1597086364816,
            26.565139162435997
          ],
          [
            114.15970848335779,
            26.56511794693701
          ],
          [
            114.15970626263035,
            26.565096659097733
          ],
          [
            114.15970167338587,
            26.565073543235325
          ],
          [
            114.1596980021532,
            26.56505116795392
          ],
          [
            114.1596943338565,
            26.565030384918185
          ],
          [
            114.15968975742274,
            26.56501285318821
          ],
          [
            114.15968348701172,
            26.564995121312407
          ],
          [
            114.15967515397705,
            26.56497346498493
          ],
          [
            114.15966566757645,
            26.564945626171603
          ],
          [
            114.15965300143507,
            26.564914551169572
          ],
          [
            114.15963624741705,
            26.564878774452115
          ],
          [
            114.15961710414079,
            26.564837237138125
          ],
          [
            114.15959673955751,
            26.564787843441923
          ],
          [
            114.15957465663942,
            26.564731419923877
          ],
          [
            114.15955210562497,
            26.56467284232293
          ],
          [
            114.15953106188364,
            26.56461404976484
          ],
          [
            114.15950737595165,
            26.564552598493535
          ],
          [
            114.15947602288205,
            26.564487873299083
          ],
          [
            114.15944470100551,
            26.564418885542633
          ],
          [
            114.15941160823854,
            26.56434701519272
          ],
          [
            114.15937389156029,
            26.56427380227529
          ],
          [
            114.15933057394041,
            26.564201683080093
          ],
          [
            114.15928394892929,
            26.56413049511169
          ],
          [
            114.15922907463388,
            26.56406543522656
          ],
          [
            114.1591688489786,
            26.564006421785603
          ],
          [
            114.15910978071574,
            26.56394525680034
          ],
          [
            114.15905041350729,
            26.563883078627377
          ],
          [
            114.15899024674671,
            26.563821007645092
          ],
          [
            114.15892905309325,
            26.563758947084843
          ],
          [
            114.15886929509716,
            26.5636954511092
          ],
          [
            114.15881130267721,
            26.56363120684349
          ],
          [
            114.15875508616742,
            26.56356724456354
          ],
          [
            114.15870171368059,
            26.563499525859147
          ],
          [
            114.15864931413755,
            26.56342979749153
          ],
          [
            114.1585946162962,
            26.563358429770012
          ],
          [
            114.15853530552906,
            26.563287647942854
          ],
          [
            114.15846959489772,
            26.56321911271744
          ],
          [
            114.15840196872313,
            26.56315209443439
          ],
          [
            114.1583329366328,
            26.563086568168988
          ],
          [
            114.1582610916014,
            26.56302181647481
          ],
          [
            114.15818937144846,
            26.562958177862647
          ],
          [
            114.15811679440566,
            26.562894781726406
          ],
          [
            114.15804530035736,
            26.56282972474516
          ],
          [
            114.15797421577929,
            26.56276429251523
          ],
          [
            114.1579020620916,
            26.562700622342287
          ],
          [
            114.15782590322178,
            26.562640527149053
          ],
          [
            114.15774688586235,
            26.56258115060545
          ],
          [
            114.15766634962463,
            26.562521979378413
          ],
          [
            114.15758629002177,
            26.562461416760772
          ],
          [
            114.15751071562865,
            26.562395969194103
          ],
          [
            114.15744156994238,
            26.56232502652132
          ],
          [
            114.15738138090559,
            26.562245940340578
          ],
          [
            114.15733534391777,
            26.56215995644319
          ],
          [
            114.15729931872377,
            26.562069823335715
          ],
          [
            114.15727190769992,
            26.561975359555216
          ],
          [
            114.15724573412287,
            26.561881385948798
          ],
          [
            114.15721374497367,
            26.561789301773644
          ],
          [
            114.15717186521444,
            26.56170171882991
          ],
          [
            114.15711753221262,
            26.561619205680252
          ],
          [
            114.15705301854895,
            26.561542426037725
          ],
          [
            114.15698171378895,
            26.56147168031197
          ],
          [
            114.15690592901431,
            26.561405951872374
          ],
          [
            114.15682732091452,
            26.561346974209584
          ],
          [
            114.15674506048151,
            26.561296141052985
          ],
          [
            114.15665879267486,
            26.56125913296765
          ],
          [
            114.15656406257126,
            26.56124411859645
          ],
          [
            114.15646669122148,
            26.56124698851595
          ],
          [
            114.15637162547847,
            26.56125938572504
          ],
          [
            114.15628422882703,
            26.561287304843177
          ],
          [
            114.15621214018637,
            26.561337451997648
          ],
          [
            114.15615932854297,
            26.561400484857458
          ],
          [
            114.1561315037868,
            26.561473721665983
          ],
          [
            114.1561179986048,
            26.56155203214409
          ],
          [
            114.15611130790742,
            26.5616331130015
          ],
          [
            114.15610912680565,
            26.561717074468532
          ],
          [
            114.15610848185317,
            26.561803864013033
          ],
          [
            114.15610849380043,
            26.561891831447568
          ],
          [
            114.15610917893405,
            26.56197820582071
          ],
          [
            114.15610465489685,
            26.562067587338525
          ],
          [
            114.15609557055673,
            26.56215640628255
          ],
          [
            114.15608317421145,
            26.562243052545792
          ],
          [
            114.15606828881043,
            26.56232977044269
          ],
          [
            114.15605379713884,
            26.56241890194499
          ],
          [
            114.15604039218884,
            26.562509263049265
          ],
          [
            114.15602752190149,
            26.56260134604075
          ],
          [
            114.15601808966495,
            26.562693900783092
          ],
          [
            114.15600877966612,
            26.562784956987425
          ],
          [
            114.1559978060135,
            26.562874591275285
          ],
          [
            114.15598247807286,
            26.562966394911967
          ],
          [
            114.15596371204576,
            26.563056010366545
          ],
          [
            114.1559431901792,
            26.56314291339736
          ],
          [
            114.15592292757809,
            26.563225608531337
          ],
          [
            114.1559161990218,
            26.56332140276761
          ],
          [
            114.15591792145044,
            26.56341774609093
          ],
          [
            114.1559372593956,
            26.56350965343817
          ],
          [
            114.15597876340011,
            26.563592908665985
          ],
          [
            114.15604584711213,
            26.56365559022157
          ],
          [
            114.15611293082412,
            26.563718271777137
          ],
          [
            114.15618401005942,
            26.563774507452717
          ],
          [
            114.15624964989924,
            26.563828708369822
          ],
          [
            114.15630663279312,
            26.563886601544496
          ],
          [
            114.15634539248205,
            26.563952131174325
          ],
          [
            114.15636287480179,
            26.564027382568728
          ],
          [
            114.1563556474552,
            26.564108608613445
          ],
          [
            114.1563288536117,
            26.564187937805038
          ],
          [
            114.15628686415035,
            26.564263092368986
          ],
          [
            114.15623378326893,
            26.56433155646463
          ],
          [
            114.15617222725949,
            26.56439805261761
          ],
          [
            114.15610552795911,
            26.56446462050127
          ],
          [
            114.15603954841407,
            26.56453339757861
          ],
          [
            114.15597295323342,
            26.56460544322152
          ],
          [
            114.15591038412846,
            26.56467809309985
          ],
          [
            114.15586742457849,
            26.56475495973929
          ],
          [
            114.15585094611427,
            26.56483722461252
          ],
          [
            114.15586165973221,
            26.56492115898213
          ],
          [
            114.15589781173334,
            26.564995767152453
          ],
          [
            114.15595415622863,
            26.565060514949018
          ],
          [
            114.15602298319858,
            26.56511778510147
          ],
          [
            114.15609860364916,
            26.565174762289853
          ],
          [
            114.15617913687315,
            26.565234141970574
          ],
          [
            114.15626394652605,
            26.565297805031573
          ],
          [
            114.15635004655941,
            26.56537074524161
          ],
          [
            114.15643614659277,
            26.565443685451662
          ],
          [
            114.15651971992243,
            26.56552846634448
          ],
          [
            114.15659609504654,
            26.56562342593668
          ],
          [
            114.15666714664029,
            26.565728509141852
          ],
          [
            114.1567343083156,
            26.56583837628096
          ],
          [
            114.15679916375645,
            26.565948756394768
          ],
          [
            114.15686287916449,
            26.566056077850924
          ],
          [
            114.1569291563945,
            26.566163505440393
          ],
          [
            114.15700382649528,
            26.56626753225493
          ],
          [
            114.15708371316849,
            26.56636819484912
          ],
          [
            114.15716457208664,
            26.566465033243645
          ],
          [
            114.15724757419224,
            26.56655510057013
          ],
          [
            114.15732999580165,
            26.566638488612327
          ],
          [
            114.1574055953006,
            26.566718452933106
          ],
          [
            114.15746837358809,
            26.566799034723147
          ],
          [
            114.15752075496307,
            26.566881027124783
          ],
          [
            114.15756325934623,
            26.566967146335102
          ],
          [
            114.15759930090547,
            26.567056191594247
          ],
          [
            114.1576302995738,
            26.56714549804786
          ],
          [
            114.1576548902583,
            26.567234120199075
          ],
          [
            114.15767524150213,
            26.56732017965793
          ],
          [
            114.1576945587018,
            26.56740239420665
          ],
          [
            114.15771327428811,
            26.567479693057052
          ],
          [
            114.15772963725023,
            26.567555210180306
          ],
          [
            114.15774550568352,
            26.567629650559702
          ],
          [
            114.1577552471172,
            26.567702251274994
          ],
          [
            114.15775441922268,
            26.567773831266475
          ],
          [
            114.15773780351715,
            26.56783972811061
          ],
          [
            114.15772118781165,
            26.56790562495473
          ],
          [
            114.15769528520063,
            26.567957377726568
          ],
          [
            114.15767249794655,
            26.5679946493897
          ],
          [
            114.15764971069241,
            26.568031921052825
          ],
          [
            114.15763334541334,
            26.5680568155908
          ],
          [
            114.15762154085787,
            26.56807600561807
          ],
          [
            114.1576118369178,
            26.56809247674941
          ],
          [
            114.15760327392836,
            26.568108234545196
          ],
          [
            114.15759508437935,
            26.568124312091378
          ],
          [
            114.15758700986244,
            26.56813945182705
          ],
          [
            114.15758031206714,
            26.56815248097333
          ],
          [
            114.15757403970464,
            26.56816207598657
          ],
          [
            114.15756918474736,
            26.568170411313282
          ],
          [
            114.15756594492876,
            26.56817794409699
          ],
          [
            114.15756263003182,
            26.568182674113693
          ],
          [
            114.15756153731891,
            26.568184233301945
          ],
          [
            114.15756117712023,
            26.568184747268
          ],
          [
            114.15756105838541,
            26.568184916690196
          ],
          [
            114.157561019246,
            26.568184972538013
          ],
          [
            114.15756100634421,
            26.568184990947515
          ],
          [
            114.1575610020913,
            26.568184997015962
          ],
          [
            114.15756100068936,
            26.56818499901636
          ],
          [
            114.15756100022725,
            26.56818499967577
          ],
          [
            114.15756100007488,
            26.56818499989318
          ],
          [
            114.15756100002459,
            26.568184999964966
          ],
          [
            114.15756100000787,
            26.568184999988986
          ],
          [
            114.15756100000185,
            26.56818499999799
          ],
          [
            114.15756099999832,
            26.568185000004267
          ],
          [
            114.15756099999248,
            26.568185000016356
          ],
          [
            114.15756099997637,
            26.56818500005075
          ],
          [
            114.15756099992797,
            26.56818500015432
          ],
          [
            114.15756099978134,
            26.568185000468283
          ],
          [
            114.15756099933658,
            26.568185001420627
          ],
          [
            114.1575609979874,
            26.568185004309697
          ],
          [
            114.15756099389445,
            26.56818501307409
          ],
          [
            114.15756098147793,
            26.568185039662094
          ],
          [
            114.15756094381074,
            26.568185120320557
          ],
          [
            114.157560829542,
            26.568185365009345
          ],
          [
            114.15756048289194,
            26.568186107307202
          ],
          [
            114.15755943128076,
            26.568188359172172
          ],
          [
            114.15755624107206,
            26.568195190521344
          ],
          [
            114.1575465631304,
            26.56821591438006
          ],
          [
            114.15753492633857,
            26.568240611347807
          ],
          [
            114.15751909929564,
            26.56826886830668
          ],
          [
            114.15750068106726,
            26.56830103556355
          ],
          [
            114.15748182804657,
            26.568337341136747
          ],
          [
            114.15746137732958,
            26.5683768383292
          ],
          [
            114.15743871446398,
            26.568418841674326
          ],
          [
            114.15741429905691,
            26.56846199245481
          ],
          [
            114.15738892807104,
            26.56850785950443
          ],
          [
            114.15736073247172,
            26.56855353501857
          ],
          [
            114.15733217215887,
            26.568604029745032
          ],
          [
            114.15730520982063,
            26.56864638535583
          ],
          [
            114.15728398663063,
            26.568676996815253
          ],
          [
            114.15726683504307,
            26.56869942426741
          ],
          [
            114.1572521851261,
            26.56871697700349
          ],
          [
            114.15723642431064,
            26.56873586166637
          ],
          [
            114.1572185153952,
            26.568758647574807
          ],
          [
            114.15719858255324,
            26.56878504286259
          ],
          [
            114.1571767173395,
            26.568814223138986
          ],
          [
            114.1571531035055,
            26.56884779744868
          ],
          [
            114.15712690422473,
            26.56888382217941
          ],
          [
            114.15709921109988,
            26.568923694324237
          ],
          [
            114.1570704424859,
            26.568964513025517
          ],
          [
            114.15704227710259,
            26.569004667845487
          ],
          [
            114.15701585276346,
            26.56904300656937
          ],
          [
            114.15698922770012,
            26.569081354249054
          ],
          [
            114.15696154977724,
            26.5691174583126
          ],
          [
            114.15693871118334,
            26.56915009735173
          ],
          [
            114.15691956868237,
            26.569178779276093
          ],
          [
            114.15690529128344,
            26.569204433738474
          ],
          [
            114.15689413753859,
            26.569229316230146
          ],
          [
            114.15688453457382,
            26.569253266554064
          ],
          [
            114.15687429710337,
            26.569274853709363
          ],
          [
            114.15686310138945,
            26.56929487815173
          ],
          [
            114.15684795406555,
            26.56931337320189
          ],
          [
            114.15682865428805,
            26.56932965047284
          ],
          [
            114.15680751993202,
            26.569345451240547
          ],
          [
            114.15678845766337,
            26.569357777341732
          ],
          [
            114.15677410914715,
            26.569367073343816
          ],
          [
            114.15676536253592,
            26.56937237950233
          ],
          [
            114.15676256326887,
            26.569374113196503
          ],
          [
            114.15676189517015,
            26.569374637931872
          ],
          [
            114.15676244743628,
            26.569374669068214
          ],
          [
            114.15676497295901,
            26.569374249053244
          ],
          [
            114.15677018817128,
            26.56937280529014
          ],
          [
            114.15677838646734,
            26.569371096084428
          ],
          [
            114.15678711162458,
            26.569366791313016
          ],
          [
            114.15679735223364,
            26.569360838765963
          ],
          [
            114.15680670975756,
            26.56935466641182
          ],
          [
            114.15681430832329,
            26.569348039283714
          ],
          [
            114.15682096394201,
            26.56934146570991
          ],
          [
            114.15682893368157,
            26.56933689030636
          ],
          [
            114.1568354497339,
            26.56933352863722
          ],
          [
            114.15684121562128,
            26.56933088764723
          ],
          [
            114.15684727546021,
            26.56932809348928
          ],
          [
            114.15685507410488,
            26.569325426783784
          ],
          [
            114.15686297377476,
            26.569321978625368
          ],
          [
            114.1568708376928,
            26.569319864605195
          ],
          [
            114.15687848034113,
            26.569317566004216
          ],
          [
            114.15688677782735,
            26.569314675746625
          ],
          [
            114.15689613570764,
            26.569311343441967
          ],
          [
            114.15690567859423,
            26.569305752788537
          ],
          [
            114.15691614659274,
            26.569299825117522
          ],
          [
            114.1569268144377,
            26.569293659033185
          ],
          [
            114.15693586603287,
            26.56928839139361
          ],
          [
            114.15694200843964,
            26.56928365733129
          ],
          [
            114.15694407252087,
            26.569279819392747
          ],
          [
            114.15694487219193,
            26.569278461791548
          ],
          [
            114.15694549762534,
            26.569277733740464
          ],
          [
            114.15694680145992,
            26.56927664270388
          ],
          [
            114.156950561183,
            26.569273701296414
          ],
          [
            114.15696053906152,
            26.569267626119462
          ],
          [
            114.15697051694006,
            26.569261550942503
          ],
          [
            114.15697983627426,
            26.569256226853017
          ],
          [
            114.15698756912788,
            26.569251212026682
          ],
          [
            114.15699471458349,
            26.569246486251416
          ],
          [
            114.15700419749176,
            26.569242423372714
          ],
          [
            114.15701531291384,
            26.569240300947012
          ],
          [
            114.15702685492435,
            26.569238588795837
          ],
          [
            114.15703956243395,
            26.569237679337373
          ],
          [
            114.15705167341964,
            26.56923633272647
          ],
          [
            114.15706606574074,
            26.569236802992773
          ],
          [
            114.15708054768507,
            26.569238367961365
          ],
          [
            114.15709441299893,
            26.56924043456331
          ],
          [
            114.15710611479065,
            26.569243093595034
          ],
          [
            114.15711524651964,
            26.569245880221896
          ],
          [
            114.15712471432316,
            26.56924850355805
          ],
          [
            114.15713924577874,
            26.56925181338545
          ],
          [
            114.15715138574404,
            26.569253505526728
          ],
          [
            114.15716132503034,
            26.569253160284983
          ],
          [
            114.15716625431463,
            26.569253033554478
          ],
          [
            114.15716880374592,
            26.56925295256723
          ],
          [
            114.15716972235136,
            26.569252806915372
          ],
          [
            114.15717026244472,
            26.569252398035413
          ],
          [
            114.15717116032269,
            26.569251168510576
          ],
          [
            114.15717364004117,
            26.56924744215736
          ],
          [
            114.15717971886627,
            26.569240228755234
          ],
          [
            114.15718541442824,
            26.56923332720991
          ],
          [
            114.15719031169378,
            26.56922687174232
          ],
          [
            114.15719427060759,
            26.569221604701372
          ],
          [
            114.15719587188104,
            26.56921852531341
          ],
          [
            114.15719729849307,
            26.56921616207352
          ],
          [
            114.1571977687573,
            26.569215383062357
          ],
          [
            114.15719792377384,
            26.56921512627151
          ],
          [
            114.15719797487304,
            26.569215041623764
          ],
          [
            114.15719799171724,
            26.569215013720733
          ],
          [
            114.15719799726969,
            26.569215004522864
          ],
          [
            114.15719799909999,
            26.569215001490914
          ],
          [
            114.15719799970331,
            26.56921500049146
          ],
          [
            114.15719799990221,
            26.56921500016201
          ],
          [
            114.15719799996776,
            26.569215000053404
          ],
          [
            114.15719799998935,
            26.56921500001761
          ],
          [
            114.15719799999648,
            26.56921500000581
          ],
          [
            114.15719799999884,
            26.569215000001922
          ],
          [
            114.1571979999996,
            26.56921500000064
          ],
          [
            114.15719799999987,
            26.56921500000021
          ],
          [
            114.15719799999997,
            26.569215000000078
          ],
          [
            114.15719799999998,
            26.569215000000032
          ],
          [
            114.157198,
            26.56921500000001
          ],
          [
            114.157198,
            26.56921500000001
          ],
          [
            114.157198,
            26.569215000000003
          ],
          [
            114.157198,
            26.569215000000003
          ],
          [
            114.157198,
            26.569215000000003
          ],
          [
            114.157198,
            26.569215000000003
          ],
          [
            114.157198,
            26.569215000000003
          ],
          [
            114.157198,
            26.569215000000003
          ],
          [
            114.157198,
            26.569215000000003
          ],
          [
            114.157198,
            26.569215000000003
          ],
          [
            114.157198,
            26.569215000000003
          ],
          [
            114.157198,
            26.569215000000003
          ],
          [
            114.157198,
            26.569215000000003
          ],
          [
            114.157198,
            26.569215000000003
          ],
          [
            114.157198,
            26.569215000000003
          ],
          [
            114.157198,
            26.569215000000003
          ],
          [
            114.157198,
            26.569215000000003
          ],
          [
            114.157198,
            26.569215000000003
          ],
          [
            114.157198,
            26.569215000000003
          ],
          [
            114.157198,
            26.569215000000003
          ],
          [
            114.157198,
            26.569215000000003
          ],
          [
            114.157198,
            26.569215000000003
          ],
          [
            114.157198,
            26.569215000000003
          ],
          [
            114.157198,
            26.569215000000003
          ],
          [
            114.157198,
            26.569215000000003
          ],
          [
            114.157198,
            26.569215000000003
          ],
          [
            114.157198,
            26.569215000000003
          ],
          [
            114.157198,
            26.569215000000003
          ],
          [
            114.157198,
            26.569215000000003
          ],
          [
            114.157198,
            26.569215
          ],
          [
            114.15719800000002,
            26.569214999999986
          ],
          [
            114.1571980000001,
            26.569214999999954
          ],
          [
            114.15719800000029,
            26.569214999999858
          ],
          [
            114.15719800000088,
            26.569214999999556
          ],
          [
            114.1571980000027,
            26.56921499999866
          ],
          [
            114.15719800000817,
            26.56921499999593
          ],
          [
            114.15719800002476,
            26.569214999987626
          ],
          [
            114.1571980000751,
            26.569214999962448
          ],
          [
            114.15719800022785,
            26.56921499988608
          ],
          [
            114.15719800069122,
            26.56921499965439
          ],
          [
            114.15719800209692,
            26.569214998951534
          ],
          [
            114.15719800636136,
            26.56921499681933
          ],
          [
            114.15719801929802,
            26.569214990350996
          ],
          [
            114.15719805854324,
            26.56921497072839
          ],
          [
            114.15719817759913,
            26.569214911200447
          ],
          [
            114.15719853877177,
            26.569214730614124
          ],
          [
            114.1571996344395,
            26.56921418278025
          ],
          [
            114.1572029583008,
            26.569212520849586
          ],
          [
            114.15721304169918,
            26.569207479150425
          ],
          [
            114.15721636556052,
            26.56920581721975
          ],
          [
            114.15721746122826,
            26.569205269385886
          ],
          [
            114.15721782240091,
            26.569205088799556
          ],
          [
            114.15721794145675,
            26.56920502927162
          ],
          [
            114.157217980702,
            26.56920500964901
          ],
          [
            114.15721799363868,
            26.56920500318067
          ],
          [
            114.15721799790308,
            26.569205001048466
          ],
          [
            114.15721799930877,
            26.56920500034561
          ],
          [
            114.15721799977214,
            26.569205000113925
          ],
          [
            114.15721799992487,
            26.569205000037552
          ],
          [
            114.15721799997524,
            26.569205000012374
          ],
          [
            114.15721799999184,
            26.56920500000408
          ],
          [
            114.15721799999731,
            26.569205000001343
          ],
          [
            114.15721799999912,
            26.569205000000444
          ],
          [
            114.15721799999972,
            26.569205000000142
          ],
          [
            114.1572179999999,
            26.569205000000053
          ],
          [
            114.15721799999996,
            26.569205000000014
          ],
          [
            114.157218,
            26.56920500000001
          ],
          [
            114.157218,
            26.569205000000004
          ],
          [
            114.157218,
            26.569205
          ],
          [
            114.157218,
            26.569205
          ],
          [
            114.157218,
            26.569205
          ],
          [
            114.157218,
            26.569205
          ],
          [
            114.157218,
            26.569205
          ],
          [
            114.157218,
            26.569205
          ],
          [
            114.157218,
            26.569205
          ],
          [
            114.157218,
            26.569205
          ],
          [
            114.157218,
            26.569205
          ],
          [
            114.157218,
            26.569205
          ],
          [
            114.157218,
            26.569205
          ],
          [
            114.157218,
            26.569205
          ],
          [
            114.157218,
            26.569205
          ],
          [
            114.157218,
            26.569205
          ],
          [
            114.157218,
            26.569205
          ],
          [
            114.157218,
            26.569205
          ],
          [
            114.157218,
            26.569205
          ],
          [
            114.157218,
            26.569205
          ],
          [
            114.157218,
            26.569205
          ],
          [
            114.157218,
            26.569205
          ],
          [
            114.157218,
            26.569205
          ],
          [
            114.157218,
            26.569205
          ],
          [
            114.157218,
            26.569205
          ],
          [
            114.157218,
            26.569205
          ],
          [
            114.157218,
            26.569205
          ],
          [
            114.157218,
            26.569205
          ],
          [
            114.157218,
            26.569205
          ],
          [
            114.157218,
            26.569205
          ],
          [
            114.157218,
            26.569205
          ],
          [
            114.157218,
            26.569205
          ],
          [
            114.157218,
            26.569205
          ],
          [
            114.157218,
            26.569205
          ],
          [
            114.157218,
            26.569205
          ],
          [
            114.157218,
            26.569205
          ],
          [
            114.157218,
            26.569205
          ],
          [
            114.157218,
            26.569205
          ],
          [
            114.157218,
            26.569205
          ],
          [
            114.157218,
            26.569205
          ],
          [
            114.157218,
            26.569205
          ],
          [
            114.157218,
            26.569205
          ],
          [
            114.157218,
            26.569205
          ],
          [
            114.157218,
            26.569205
          ],
          [
            114.157218,
            26.569205
          ],
          [
            114.157218,
            26.569205
          ],
          [
            114.157218,
            26.569205
          ],
          [
            114.157218,
            26.569205
          ],
          [
            114.157218,
            26.569205
          ],
          [
            114.157218,
            26.569205
          ],
          [
            114.157218,
            26.569205
          ],
          [
            114.157218,
            26.569205
          ],
          [
            114.157218,
            26.569205
          ],
          [
            114.157218,
            26.569205
          ],
          [
            114.157218,
            26.569205
          ],
          [
            114.157218,
            26.569205
          ],
          [
            114.157218,
            26.569205
          ],
          [
            114.157218,
            26.569205
          ],
          [
            114.157218,
            26.569205
          ],
          [
            114.157218,
            26.569205
          ],
          [
            114.157218,
            26.569205
          ],
          [
            114.157218,
            26.569205
          ],
          [
            114.157218,
            26.569205
          ],
          [
            114.157218,
            26.569205
          ],
          [
            114.157218,
            26.569205
          ],
          [
            114.157218,
            26.569205
          ],
          [
            114.157218,
            26.569205
          ],
          [
            114.157218,
            26.569205
          ],
          [
            114.157218,
            26.569205
          ],
          [
            114.157218,
            26.569205
          ],
          [
            114.157218,
            26.569205
          ],
          [
            114.157218,
            26.569205
          ],
          [
            114.157218,
            26.569205
          ],
          [
            114.157218,
            26.569205
          ],
          [
            114.157218,
            26.569205
          ],
          [
            114.157218,
            26.569205
          ],
          [
            114.157218,
            26.569205
          ],
          [
            114.157218,
            26.569205
          ],
          [
            114.157218,
            26.569205
          ],
          [
            114.157218,
            26.569205
          ],
          [
            114.157218,
            26.569205
          ],
          [
            114.157218,
            26.569205
          ],
          [
            114.157218,
            26.569205
          ],
          [
            114.157218,
            26.569205
          ],
          [
            114.157218,
            26.569205
          ],
          [
            114.157218,
            26.569205
          ],
          [
            114.157218,
            26.569205
          ],
          [
            114.157218,
            26.569205
          ],
          [
            114.157218,
            26.569205
          ],
          [
            114.157218,
            26.569205
          ],
          [
            114.157218,
            26.569205
          ],
          [
            114.157218,
            26.569205
          ],
          [
            114.157218,
            26.569205
          ],
          [
            114.157218,
            26.569205
          ],
          [
            114.157218,
            26.569205
          ],
          [
            114.157218,
            26.569205
          ],
          [
            114.157218,
            26.569205
          ],
          [
            114.157218,
            26.569205
          ],
          [
            114.157218,
            26.569205
          ],
          [
            114.157218,
            26.569205
          ],
          [
            114.157218,
            26.569205
          ],
          [
            114.157218,
            26.569205
          ],
          [
            114.157218,
            26.569205
          ],
          [
            114.157218,
            26.569205
          ],
          [
            114.157218,
            26.569205
          ],
          [
            114.157218,
            26.569205
          ],
          [
            114.157218,
            26.569205
          ],
          [
            114.157218,
            26.569205
          ],
          [
            114.157218,
            26.569205
          ],
          [
            114.157218,
            26.569205
          ],
          [
            114.157218,
            26.569205
          ],
          [
            114.157218,
            26.569205
          ],
          [
            114.157218,
            26.569205
          ],
          [
            114.157218,
            26.569205
          ],
          [
            114.157218,
            26.569205
          ],
          [
            114.157218,
            26.569205
          ],
          [
            114.157218,
            26.569205
          ],
          [
            114.157218,
            26.569205
          ],
          [
            114.157218,
            26.569205
          ],
          [
            114.157218,
            26.569205
          ],
          [
            114.157218,
            26.569205
          ],
          [
            114.157218,
            26.569205
          ],
          [
            114.157218,
            26.569205
          ],
          [
            114.157218,
            26.569205
          ],
          [
            114.157218,
            26.569205
          ],
          [
            114.157218,
            26.569205
          ],
          [
            114.157218,
            26.569205
          ],
          [
            114.157218,
            26.569205
          ],
          [
            114.157218,
            26.569205
          ],
          [
            114.157218,
            26.569205
          ],
          [
            114.157218,
            26.569205
          ],
          [
            114.157218,
            26.569205
          ],
          [
            114.157218,
            26.569205
          ],
          [
            114.157218,
            26.569205
          ],
          [
            114.157218,
            26.569205
          ],
          [
            114.157218,
            26.569205
          ],
          [
            114.157218,
            26.569205
          ],
          [
            114.157218,
            26.569205
          ],
          [
            114.157218,
            26.569205
          ],
          [
            114.157218,
            26.569205
          ],
          [
            114.157218,
            26.569205
          ],
          [
            114.157218,
            26.569205
          ],
          [
            114.157218,
            26.569205
          ],
          [
            114.157218,
            26.569205
          ],
          [
            114.157218,
            26.569205
          ],
          [
            114.157218,
            26.569205
          ],
          [
            114.157218,
            26.569205
          ],
          [
            114.157218,
            26.569205
          ],
          [
            114.157218,
            26.569205
          ],
          [
            114.157218,
            26.569205
          ],
          [
            114.157218,
            26.569205
          ],
          [
            114.157218,
            26.569205
          ],
          [
            114.157218,
            26.569205
          ],
          [
            114.157218,
            26.569205
          ],
          [
            114.157218,
            26.569205
          ],
          [
            114.157218,
            26.569205
          ],
          [
            114.157218,
            26.569205
          ],
          [
            114.157218,
            26.569205
          ],
          [
            114.157218,
            26.569205
          ],
          [
            114.157218,
            26.569205
          ],
          [
            114.157218,
            26.569205
          ],
          [
            114.157218,
            26.569205
          ],
          [
            114.157218,
            26.569205
          ],
          [
            114.157218,
            26.569205
          ],
          [
            114.157218,
            26.569205
          ],
          [
            114.157218,
            26.569205
          ],
          [
            114.157218,
            26.569205
          ],
          [
            114.157218,
            26.569205
          ],
          [
            114.157218,
            26.569205
          ],
          [
            114.157218,
            26.569205
          ],
          [
            114.157218,
            26.569205
          ],
          [
            114.157218,
            26.569205
          ],
          [
            114.157218,
            26.569205
          ],
          [
            114.157218,
            26.569205
          ],
          [
            114.157218,
            26.569205
          ],
          [
            114.157218,
            26.569205
          ],
          [
            114.157218,
            26.569205
          ],
          [
            114.157218,
            26.569205
          ],
          [
            114.157218,
            26.569205
          ],
          [
            114.157218,
            26.569205
          ],
          [
            114.157218,
            26.569205
          ],
          [
            114.157218,
            26.569205
          ],
          [
            114.157218,
            26.569205
          ],
          [
            114.157218,
            26.569205
          ],
          [
            114.157218,
            26.569205
          ],
          [
            114.157218,
            26.569205
          ],
          [
            114.157218,
            26.569205
          ],
          [
            114.157218,
            26.569205
          ],
          [
            114.157218,
            26.569205
          ]
        ]
      }
    }
  ]
}